setup.py
sensor/BMP180.py
sensor/DS18B20.py
sensor/HTU21D.py
sensor/MCP3004.py
sensor/SHT20.py
sensor/__init__.py
sensor/util.py
sensor.egg-info/PKG-INFO
sensor.egg-info/SOURCES.txt
sensor.egg-info/dependency_links.txt
sensor.egg-info/top_level.txt